partlets/__init__.py
partlets-0.0.1.dist-info/LICENSE
partlets-0.0.1.dist-info/METADATA
partlets-0.0.1.dist-info/WHEEL
partlets-0.0.1.dist-info/top_level.txt
partlets-0.0.1.dist-info/RECORD
